README.rst
setup.py
migraine/__init__.py
migraine/magic.py
migraine/migrators.py
migraine.egg-info/PKG-INFO
migraine.egg-info/SOURCES.txt
migraine.egg-info/dependency_links.txt
migraine.egg-info/requires.txt
migraine.egg-info/top_level.txt