Metadata-Version: 1.1
Name: migraine
Version: 0.0.1
Summary: Migraine helps with painful data migrations.
Home-page: http://github.com/21strun/migraine
Author: 21 strun
Author-email: adm@21s.pl
License: MIT
Keywords: django,migration,database
Platform: UNKNOWN
Classifier: Framework :: Django
Classifier: Intended Audience :: Developers
Classifier: License :: OSI Approved :: MIT License
Classifier: Operating System :: OS Independent
Classifier: Topic :: Database
Classifier: Programming Language :: Python :: 2
Classifier: Programming Language :: Python :: 2.7
